plex_course_renamer/__init__.py
plex_course_renamer/rename.py
plex_course_renamer-0.0.2.dist-info/entry_points.txt
plex_course_renamer-0.0.2.dist-info/LICENSE
plex_course_renamer-0.0.2.dist-info/WHEEL
plex_course_renamer-0.0.2.dist-info/METADATA
plex_course_renamer-0.0.2.dist-info/RECORD
